langfair/__init__.py
langfair/auto/__init__.py
langfair/auto/auto.py
langfair/constants/__init__.py
langfair/constants/cost_data.py
langfair/constants/word_lists.py
langfair/generator/__init__.py
langfair/generator/counterfactual.py
langfair/generator/generator.py
langfair/metrics/__init__.py
langfair/metrics/classification/__init__.py
langfair/metrics/classification/classification.py
langfair/metrics/classification/metrics/__init__.py
langfair/metrics/classification/metrics/baseclass/__init__.py
langfair/metrics/classification/metrics/baseclass/metrics.py
langfair/metrics/classification/metrics/false_discovery.py
langfair/metrics/classification/metrics/false_negative.py
langfair/metrics/classification/metrics/false_omission.py
langfair/metrics/classification/metrics/false_positive.py
langfair/metrics/classification/metrics/predicted_prevalence.py
langfair/metrics/counterfactual/__init__.py
langfair/metrics/counterfactual/counterfactual.py
langfair/metrics/counterfactual/metrics/__init__.py
langfair/metrics/counterfactual/metrics/baseclass/__init__.py
langfair/metrics/counterfactual/metrics/baseclass/metrics.py
langfair/metrics/counterfactual/metrics/bleu.py
langfair/metrics/counterfactual/metrics/cosine.py
langfair/metrics/counterfactual/metrics/rougel.py
langfair/metrics/counterfactual/metrics/sentimentbias.py
langfair/metrics/recommendation/__init__.py
langfair/metrics/recommendation/metrics/__init__.py
langfair/metrics/recommendation/metrics/baseclass/__init__.py
langfair/metrics/recommendation/metrics/baseclass/metrics.py
langfair/metrics/recommendation/metrics/jaccard.py
langfair/metrics/recommendation/metrics/prag.py
langfair/metrics/recommendation/metrics/serp.py
langfair/metrics/recommendation/recommendation.py
langfair/metrics/stereotype/__init__.py
langfair/metrics/stereotype/metrics/__init__.py
langfair/metrics/stereotype/metrics/associations.py
langfair/metrics/stereotype/metrics/baseclass/__init__.py
langfair-1.0.0.dist-info/LICENSE
langfair-1.0.0.dist-info/METADATA
langfair-1.0.0.dist-info/WHEEL
langfair-1.0.0.dist-info/RECORD
