Metadata-Version: 2.1
Name: langfair
Version: 1.0.0
Summary: Bias and Fairness Assessments for Language Models
Home-page: https://github.com/cvs-health/langfair
Author: Dylan Bouchard
Author-email: dylan.bouchard@cvshealth.com
Requires-Python: >=3.9,<3.12
Classifier: Operating System :: OS Independent
Classifier: Programming Language :: Python :: 3
Classifier: Programming Language :: Python :: 3.9
Classifier: Programming Language :: Python :: 3.10
Classifier: Programming Language :: Python :: 3.11
Classifier: Programming Language :: Python :: 3 :: Only
Classifier: Topic :: Scientific/Engineering :: Artificial Intelligence
Classifier: Topic :: Software Development :: Libraries :: Python Modules
Requires-Dist: asyncio (>=3.4.3,<4.0.0)
Requires-Dist: detoxify (>=0.5.2,<0.6.0)
Requires-Dist: evaluate (>=0.4.1,<0.5.0)
Requires-Dist: langchain (>=0.1.13,<0.2.0)
Requires-Dist: langchain-openai (>=0.1.6,<0.2.0)
Requires-Dist: nltk (>=3.8.2)
Requires-Dist: numpy (>=1.26.4,<2.0.0)
Requires-Dist: openai (>=1.24.0,<2.0.0)
Requires-Dist: rouge-score (>=0.1.2,<0.2.0)
Requires-Dist: sacremoses (>=0.1.1,<0.2.0)
Requires-Dist: scikit-learn (>=1.4.2,<2.0.0)
Requires-Dist: scipy (>=1.10.1,<2.0.0)
Requires-Dist: sentence-transformers (>=2.7.0,<3.0.0)
Requires-Dist: tiktoken (>=0.6.0,<0.7.0)
Requires-Dist: typing (<3.10)
Requires-Dist: vadersentiment (>=3.3.2,<4.0.0)
Project-URL: Repository, https://github.com/cvs-health/langfair
